fhirpath_guillotina/__init__.py
fhirpath_guillotina/engine.py
fhirpath_guillotina/field.py
fhirpath_guillotina/helpers.py
fhirpath_guillotina/interfaces.py
fhirpath_guillotina/utilities.py
fhirpath_guillotina-0.4.0.dist-info/AUTHORS.rst
fhirpath_guillotina-0.4.0.dist-info/LICENSE
fhirpath_guillotina-0.4.0.dist-info/METADATA
fhirpath_guillotina-0.4.0.dist-info/WHEEL
fhirpath_guillotina-0.4.0.dist-info/entry_points.txt
fhirpath_guillotina-0.4.0.dist-info/top_level.txt
fhirpath_guillotina-0.4.0.dist-info/RECORD
