Metadata-Version: 2.1
Name: fhirpath-guillotina
Version: 0.4.0
Summary: A guillotina framework powered fhirpath provider.
Home-page: https://github.com/nazrulworld/fhirpath_guillotina
Author: Md Nazrul Islam
Author-email: email2nazrul@gmail.com
License: GNU General Public License v3
Project-URL: CI: Travis, https://travis-ci.com/nazrulworld/fhirpath_guillotina
Project-URL: Coverage: codecov, https://codecov.io/github/nazrulworld/fhirpath_guillotina
Project-URL: Docs: RTD, https://fhirpath-guillotina.readthedocs.io/
Project-URL: GitHub: issues, https://github.com/nazrulworld/fhirpath_guillotina/issues
Project-URL: GitHub: repo, https://github.com/nazrulworld/fhirpath_guillotina
Keywords: fhirpath guillotina hl7 fhir fhirpath
Platform: UNKNOWN
Classifier: Development Status :: 4 - Beta
Classifier: License :: OSI Approved :: GNU General Public License v3 (GPLv3)
Classifier: Intended Audience :: Developers
Classifier: Intended Audience :: Healthcare Industry
Classifier: Natural Language :: English
Classifier: Programming Language :: Python :: 3
Classifier: Programming Language :: Python :: 3.7
Classifier: Programming Language :: Python :: 3.8
Classifier: Programming Language :: Python :: 3.9
Requires-Python: >=3.7
Requires-Dist: Click (>=6.0)
Requires-Dist: guillotina (<6.0.0a1,>=5.3.39)
Requires-Dist: guillotina-elasticsearch (==5.0.0)
Requires-Dist: fhirpath (>=0.6.1)
Provides-Extra: docs
Requires-Dist: sphinx ; extra == 'docs'
Requires-Dist: sphinx-rtd-theme ; extra == 'docs'
Requires-Dist: sphinxcontrib-httpdomain ; extra == 'docs'
Requires-Dist: sphinxcontrib-httpexample ; extra == 'docs'
Provides-Extra: test
Requires-Dist: pytest (>=5.4.0) ; extra == 'test'
Requires-Dist: pytest-asyncio (>=0.10.0) ; extra == 'test'
Requires-Dist: pytest-cov ; extra == 'test'
Requires-Dist: pytest-mock ; extra == 'test'
Requires-Dist: pytest-docker-fixtures ; extra == 'test'
Requires-Dist: async-asgi-testclient ; extra == 'test'
Requires-Dist: pytest-runner ; extra == 'test'
Provides-Extra: travis
Requires-Dist: pytest (>=5.4.0) ; extra == 'travis'
Requires-Dist: pytest-asyncio (>=0.10.0) ; extra == 'travis'
Requires-Dist: pytest-cov ; extra == 'travis'
Requires-Dist: pytest-mock ; extra == 'travis'
Requires-Dist: pytest-docker-fixtures ; extra == 'travis'
Requires-Dist: async-asgi-testclient ; extra == 'travis'
Requires-Dist: pytest-runner ; extra == 'travis'
Requires-Dist: flake8 (==3.7.8) ; extra == 'travis'
Requires-Dist: flake8-isort (==2.7.0) ; extra == 'travis'
Requires-Dist: isort ; extra == 'travis'
Requires-Dist: black ; extra == 'travis'
